blueqat/__init__.py
blueqat/_version.py
blueqat/circuit.py
blueqat/decorators.py
blueqat/gate.py
blueqat/gateset.py
blueqat/parameter.py
blueqat/parametrized_circuit.py
blueqat/pauli.py
blueqat/typing.py
blueqat/utils.py
blueqat/vqe.py
blueqat/backends/__init__.py
blueqat/backends/_numba_backend_impl.py
blueqat/backends/backendbase.py
blueqat/backends/cusv.py
blueqat/backends/cutn.py
blueqat/backends/draw_backend.py
blueqat/backends/ibmq_backend.py
blueqat/backends/manyqubitgate_fallbacker.py
blueqat/backends/numba_backend.py
blueqat/backends/numpy_backend.py
blueqat/backends/onequbitgate_decomposer.py
blueqat/backends/onequbitgate_transpiler.py
blueqat/backends/qasm_output_backend.py
blueqat/backends/qasm_parser_backend_generator.py
blueqat/backends/quimb.py
blueqat/backends/sympy_backend.py
blueqat/backends/twoqubitgate_transpiler.py
blueqat/circuit_funcs/__init__.py
blueqat/circuit_funcs/circuit_to_unitary.py
blueqat/circuit_funcs/flatten.py
blueqat/circuit_funcs/json_serializer.py
blueqat/macros/__init__.py
blueqat-2.0.4.dist-info/LICENSE
blueqat-2.0.4.dist-info/METADATA
blueqat-2.0.4.dist-info/WHEEL
blueqat-2.0.4.dist-info/top_level.txt
blueqat-2.0.4.dist-info/RECORD
