Metadata-Version: 2.1
Name: blueqat
Version: 2.0.4
Summary: Quantum Computer Library for Everyone
Home-page: https://github.com/Blueqat/Blueqat
Author: The Blueqat Developers
Author-email: info@blueqat.com
License: Apache 2
Classifier: Programming Language :: Python :: 3
Classifier: License :: OSI Approved :: Apache Software License
Classifier: Development Status :: 3 - Alpha
License-File: LICENSE
Requires-Dist: numpy (>=1.21.0)
Requires-Dist: scipy (>=1.5)
Requires-Dist: networkx (>=2.6.3)
Requires-Dist: matplotlib (>=3.5.1)
Requires-Dist: autoray (>=0.2.5)
Requires-Dist: quimb (==1.4.0)
Requires-Dist: opt-einsum (>=3.3.0)
